dc_converter-0.1.8.dist-info/METADATA
dc_converter-0.1.8.dist-info/WHEEL
dc_converter-0.1.8.dist-info/license_files/LICENSE.txt
dc_converter.libs/libkmlengine-cab7ab5e.so.1
dc_converter.libs/libnettle-2d3bda6c.so.8
dc_converter.libs/libsz-53f3c9c7.so.2
dc_converter.libs/libspatialite-72b66ed8.so.7
dc_converter.libs/libnuma-3582bce9.so.1
dc_converter.libs/libx265-a72e1820.so.199
dc_converter.libs/libzstd-5df4f4df.so.1
dc_converter.libs/libjbig-32ed19ff.so.0
dc_converter.libs/libhdf5_serial-12e4461a.so.103
dc_converter.libs/libgif-4be852f8.so.7
dc_converter.libs/librttopo-6f9dbbad.so.1
dc_converter.libs/libbz2-5e516f77.so.1.0
dc_converter.libs/libHalf-2_5-da60cc87.so.25
dc_converter.libs/libkmlbase-3d56a365.so.1
dc_converter.libs/libgdcmMSFF-54484fd8.so.3.0
dc_converter.libs/libgdal-67fc9462.so.30
dc_converter.libs/libgeos-b7fdc237.so.3.10.2
dc_converter.libs/libnetcdf-729d28c6.so.19
dc_converter.libs/libopenblas-1dedc9fe.so.0
dc_converter.libs/libmysqlclient-5d99ea2e.so.21
dc_converter.libs/libjpeg-2cfbcf67.so.8
dc_converter.libs/libogdi-5a2e34fa.so.4.1
dc_converter.libs/libgdcmjpeg8-c2c6ec1e.so.3.0
dc_converter.libs/libqhull_r-e92ac43c.so.8.0
dc_converter.libs/libicuuc-4683f362.so.70
dc_converter.libs/libarmadillo-098bd5e5.so.10
dc_converter.libs/libunistring-9c28d595.so.2
dc_converter.libs/libgdcmjpeg16-682d45b4.so.3.0
dc_converter.libs/libproj-0cb7e342.so.22
dc_converter.libs/libaom-1d6fe4ba.so.3
dc_converter.libs/libopencv_imgcodecs-2b72b44d.so.4.5d
dc_converter.libs/libtasn1-02557ad1.so.6
dc_converter.libs/libcom_err-a2b7c9d2.so.2
dc_converter.libs/libIex-2_5-c16c5aa2.so.25
dc_converter.libs/libsuperlu-17cfc126.so.5
dc_converter.libs/libuuid-1c523104.so.1
dc_converter.libs/libgdcmDSED-589e0299.so.3.0
dc_converter.libs/libkeyutils-ad20d5fb.so.1
dc_converter.libs/libodbcinst-77925e46.so.2
dc_converter.libs/libsmime3-e163e1ff.so
dc_converter.libs/liblapack-426b4bf5.so.3
dc_converter.libs/libffi-247da4d5.so.8
dc_converter.libs/libfyba-d06192ca.so.0
dc_converter.libs/libImath-2_5-13531199.so.25
dc_converter.libs/libsnappy-0b6e39db.so.1
dc_converter.libs/libcrypto-a50d99cb.so.3
dc_converter-0.1.8.dist-info/RECORD
